{
  "processes": {
    "last updated": "updatedat",
    "process id": "processnumber",
    "srcr #": "srcrnumber",
    "date created": "createdat",
    "ready for scrum date": "readyscrumdate",
    "process owner": "processownername",
    "pm assigned": "assignedpm",
    "status": "processstatus",
    "average time per transaction (mins)": "avgtimetransaction",
    "number of full time assocates": "nofulltimeassociates",
    "budget (estimate)": "estimatedbudget",
    "complexity": "tshirtsize",
    "budget (actual)": "actualbudget",
    "cost avoidance dollar amount": "costavoidedamount",
    "cost of one full time associate": "costonefulltimeassociate",
    "expense reduction dollar amount": "expensereductionamount",
    "headcount reduction amount (estimate)": "headcountreductionamount",
    "revenue generated dollar amount": "revenuegeneratedamount",
    "cost avoidance": "costavoided",
    "associate/customer experience": "associateengagement",
    "dollar amount charged": "chargedamount",
    "production machine(s)": "productionmachine",
    "business approval": "businessapprovalapproved",
    "business approval by": "businessapprovalapprovedby",
    "number of transactions per frequency (estimate)": "esttransactionfrequency"
  },
  "requests": {
    "request id": "requestid",
    "process id": "processid",

    "service type": "servicetype",
    "date created": "createdat",
    "last updated": "updatedat",

    "process owner": "request user",

    "overall status code": "overallstatuscode"
  }
}
